SyncAsyncRetry/SyncAsyncRetry.py
SyncAsyncRetry/__init__.py
SyncAsyncRetry-1.0.0.dist-info/LICENSE
SyncAsyncRetry-1.0.0.dist-info/METADATA
SyncAsyncRetry-1.0.0.dist-info/WHEEL
SyncAsyncRetry-1.0.0.dist-info/top_level.txt
SyncAsyncRetry-1.0.0.dist-info/RECORD
