Metadata-Version: 2.1
Name: SyncAsyncRetry
Version: 1.0.0
Summary: Retry decorator for both synchronous and asynchronous functions.
Home-page: https://github.com/monk-after-90s/SyncAsyncRetry.git
Author: Antas
Author-email: 
License: UNKNOWN
Platform: UNKNOWN
Classifier: Programming Language :: Python :: 3
Classifier: License :: OSI Approved :: MIT License
Classifier: Operating System :: OS Independent
Requires-Python: >=3.6
